[
  { "rank":  "1st", "id":  16, "name": "treble"   },
  { "rank":  "2nd", "id":  20, "name": "shiro"    },
  { "rank":  "3rd", "id":  26, "name": "luca"     },
  { "rank":  "4th", "id":  89, "name": "artorias" },
  { "rank":  "5th", "id":  97, "name": "nimdo"    },
  { "rank":  "6th", "id": 109, "name": "vladdy"   },
  { "rank":  "7th", "id": 176, "name": "nicks"    },
  { "rank":  "8th", "id": 190, "name": "kimura"   },
  { "rank":  "9th", "id": 267, "name": "nyushki"  },
  { "rank": "10th", "id": 299, "name": "slushy"   }
]
